teamverify/__init__.py
teamverify/competitivePokedex.csv
teamverify/geckodriver.exe
teamverify/java.exe
teamverify/pokemonBase.owl
teamverify/pokemonprod.owl
teamverify/prepareOntology.py
teamverify/readTeamSyntax.py
teamverify/reasonertest.py
teamverify/scrapePokedex.py
teamverify/teambuilder.py
teamverify-0.0.6.dist-info/LICENSE
teamverify-0.0.6.dist-info/METADATA
teamverify-0.0.6.dist-info/WHEEL
teamverify-0.0.6.dist-info/entry_points.txt
teamverify-0.0.6.dist-info/top_level.txt
teamverify-0.0.6.dist-info/RECORD
