Metadata-Version: 2.1
Name: teamverify
Version: 0.0.6
Summary: Automated reasoning tool for competitive Pokemon teambuilding
Home-page: https://github.com/danielverd/teamverify
Author: danielverd
License: UNKNOWN
Platform: UNKNOWN
Classifier: Programming Language :: Python :: 3
Classifier: License :: OSI Approved :: MIT License
Classifier: Operating System :: OS Independent
Requires-Python: >=3.6
Requires-Dist: owlready2 (>=0.23)
Requires-Dist: selenium
Requires-Dist: pandas
Requires-Dist: beautifulsoup4
Requires-Dist: requests
